{
  "IcoMoonType": "selection",
  "icons": [
    {
      "icon": {
        "paths": [
          "M384 690l452-452 60 60-512 512-238-238 60-60z"
        ],
        "attrs": [],
        "isMulticolor": false,
        "isMulticolor2": false,
        "tags": [
          "check"
        ],
        "defaultCode": 58826,
        "grid": 24
      },
      "attrs": [],
      "properties": {
        "ligatures": "check",
        "id": 148,
        "order": 4,
        "prevSize": 24,
        "code": 58826,
        "name": "tick"
      },
      "setIdx": 0,
      "setId": 2,
      "iconIdx": 148
    },
    {
      "icon": {
        "paths": [
          "M512 342l256 256-60 60-196-196-196 196-60-60z"
        ],
        "attrs": [],
        "isMulticolor": false,
        "isMulticolor2": false,
        "tags": [
          "expand_less"
        ],
        "defaultCode": 58830,
        "grid": 24
      },
      "attrs": [],
      "properties": {
        "ligatures": "expand_less",
        "id": 255,
        "order": 2,
        "prevSize": 24,
        "code": 58830,
        "name": "expand_less"
      },
      "setIdx": 0,
      "setId": 2,
      "iconIdx": 255
    },
    {
      "icon": {
        "paths": [
          "M708 366l60 60-256 256-256-256 60-60 196 196z"
        ],
        "attrs": [],
        "isMulticolor": false,
        "isMulticolor2": false,
        "tags": [
          "expand_more"
        ],
        "defaultCode": 58831,
        "grid": 24
      },
      "attrs": [],
      "properties": {
        "ligatures": "expand_more",
        "id": 256,
        "order": 3,
        "prevSize": 24,
        "code": 58831,
        "name": "expand_more"
      },
      "setIdx": 0,
      "setId": 2,
      "iconIdx": 256
    },
    {
      "icon": {
        "paths": [
          "M470 384v-86h84v86h-84zM512 854c188 0 342-154 342-342s-154-342-342-342-342 154-342 342 154 342 342 342zM512 86c236 0 426 190 426 426s-190 426-426 426-426-190-426-426 190-426 426-426zM470 726v-256h84v256h-84z"
        ],
        "attrs": [],
        "isMulticolor": false,
        "isMulticolor2": false,
        "tags": [
          "info_outline"
        ],
        "defaultCode": 59535,
        "grid": 24
      },
      "attrs": [],
      "properties": {
        "ligatures": "info_outline",
        "id": 401,
        "order": 6,
        "prevSize": 24,
        "code": 59535,
        "name": "info_outline"
      },
      "setIdx": 0,
      "setId": 2,
      "iconIdx": 401
    },
    {
      "icon": {
        "paths": [
          "M512 776l136-136 60 60-196 196-196-196 60-60zM512 248l-136 136-60-60 196-196 196 196-60 60z"
        ],
        "attrs": [],
        "isMulticolor": false,
        "isMulticolor2": false,
        "tags": [
          "unfold_more"
        ],
        "defaultCode": 58839,
        "grid": 24
      },
      "attrs": [],
      "properties": {
        "ligatures": "unfold_more",
        "id": 786,
        "order": 8,
        "prevSize": 24,
        "code": 58839,
        "name": "unfold_more"
      },
      "setIdx": 0,
      "setId": 2,
      "iconIdx": 786
    },
    {
      "icon": {
        "paths": [
          "M384 640l128-64 448-448-64-64-448 448-64 128zM289.3 867.098c-31.632-66.728-65.666-100.762-132.396-132.394l99.096-272.792 128-77.912 384-384h-192l-384 384-192 640 640-192 384-384v-192l-384 384-77.912 128z"
        ],
        "tags": [
          "pencil",
          "write",
          "edit"
        ],
        "defaultCode": 59654,
        "grid": 16,
        "attrs": []
      },
      "attrs": [],
      "properties": {
        "ligatures": "pencil2, write2",
        "name": "pencil",
        "order": 7,
        "id": 7,
        "prevSize": 32,
        "code": 59654
      },
      "setIdx": 1,
      "setId": 1,
      "iconIdx": 6
    },
    {
      "icon": {
        "paths": [
          "M832 192v-128h-640v128h-192v128c0 106.038 85.958 192 192 192 20.076 0 39.43-3.086 57.62-8.802 46.174 66.008 116.608 113.796 198.38 130.396v198.406h-64c-70.694 0-128 57.306-128 128h512c0-70.694-57.306-128-128-128h-64v-198.406c81.772-16.6 152.206-64.386 198.38-130.396 18.19 5.716 37.544 8.802 57.62 8.802 106.042 0 192-85.962 192-192v-128h-192zM192 436c-63.962 0-116-52.038-116-116v-64h116v64c0 40.186 7.43 78.632 20.954 114.068-6.802 1.246-13.798 1.932-20.954 1.932zM948 320c0 63.962-52.038 116-116 116-7.156 0-14.152-0.686-20.954-1.932 13.524-35.436 20.954-73.882 20.954-114.068v-64h116v64z"
        ],
        "tags": [
          "trophy",
          "cup",
          "prize",
          "award",
          "winner",
          "tournament"
        ],
        "defaultCode": 59806,
        "grid": 16,
        "attrs": []
      },
      "attrs": [],
      "properties": {
        "ligatures": "trophy, cup",
        "name": "trophy",
        "order": 5,
        "id": 159,
        "prevSize": 32,
        "code": 59806
      },
      "setIdx": 1,
      "setId": 1,
      "iconIdx": 158
    }
  ],
  "height": 1024,
  "metadata": {
    "name": "icomoon"
  },
  "preferences": {
    "showGlyphs": true,
    "showQuickUse": true,
    "showQuickUse2": true,
    "showSVGs": true,
    "fontPref": {
      "prefix": "icon-",
      "metadata": {
        "fontFamily": "icomoon"
      },
      "metrics": {
        "emSize": 1024,
        "baseline": 6.25,
        "whitespace": 50
      },
      "embed": false
    },
    "imagePref": {
      "prefix": "icon-",
      "png": true,
      "useClassSelector": true,
      "color": 0,
      "bgColor": 16777215,
      "classSelector": ".icon"
    },
    "historySize": 50,
    "showCodes": true,
    "gridSize": 16
  }
}